cure/__init__.py
cure/__version__.py
cure/__version_data__.py
cure/builder.py
cure/py.typed
cure-0.5.1.dist-info/LICENSE
cure-0.5.1.dist-info/WHEEL
cure-0.5.1.dist-info/METADATA
cure-0.5.1.dist-info/RECORD
